setup.py
mnes/__init__.py
mnes.egg-info/PKG-INFO
mnes.egg-info/SOURCES.txt
mnes.egg-info/dependency_links.txt
mnes.egg-info/not-zip-safe
mnes.egg-info/top_level.txt