Metadata-Version: 1.0
Name: mnes
Version: 0.1
Summary: metadata capture resistant secure messaging
Home-page: http://github.com/mnes-io/mnes
Author: Charles Perkins
Author-email: charlesap@gmail.com
License: MIT
Platform: UNKNOWN
